{
    "productId": "sodimm-kingston-value-ram-ddr4-3200-8gb",
    "product": {
        "id": "sodimm-kingston-value-ram-ddr4-3200-8gb",
        "name": "Kingston ValueRAM DDR4-3200 8GB"
    },
    "prices": [
        {
            "catalog": "catalog-acme-electronics",
            "currency": "USD",
            "list": 21.99,
            "minQuantity": 1,
            "pricelistId": "pricelist-acme-usd",
            "productId": "sodimm-kingston-value-ram-ddr4-3200-8gb"
        },
        {
            "catalog": "catalog-acme-electronics",
            "currency": "EUR",
            "list": 20.99,
            "minQuantity": 1,
            "pricelistId": "pricelist-acme-eur",
            "productId": "sodimm-kingston-value-ram-ddr4-3200-8gb"
        }
    ]
}
